dioivo_meta
